pathtype/__init__.py
pathtype/path.py
pathtype/validation.py
pathtype-1.0.0.dist-info/LICENSE
pathtype-1.0.0.dist-info/METADATA
pathtype-1.0.0.dist-info/WHEEL
pathtype-1.0.0.dist-info/top_level.txt
pathtype-1.0.0.dist-info/RECORD
