Metadata-Version: 2.1
Name: pathtype
Version: 1.0.0
Summary: Easily validate paths in command line arguments. To be used with argparse.
Home-page: https://github.com/xfrenette/pathtype
Author: Xavier Frenette
License: MIT
Keywords: argparse,argument parsing,path,pathlib,cli,command line
Classifier: Development Status :: 5 - Production/Stable
Classifier: Intended Audience :: Developers
Classifier: Operating System :: OS Independent
Classifier: Programming Language :: Python
Classifier: Programming Language :: Python :: 3.7
Classifier: Programming Language :: Python :: 3.8
Classifier: Programming Language :: Python :: 3.9
Classifier: Programming Language :: Python :: 3.10
Classifier: Topic :: Software Development :: Libraries
Classifier: Topic :: Software Development :: Libraries :: Python Modules
Requires-Python: >=3.7
License-File: LICENSE
